tensorly/__init__.py
tensorly/_factorized_tensor.py
tensorly/base.py
tensorly/cp_tensor.py
tensorly/parafac2_tensor.py
tensorly/plugins.py
tensorly/testing.py
tensorly/tr_tensor.py
tensorly/tt_matrix.py
tensorly/tt_tensor.py
tensorly/tucker_tensor.py
tensorly/backend/__init__.py
tensorly/backend/core.py
tensorly/backend/cupy_backend.py
tensorly/backend/jax_backend.py
tensorly/backend/mxnet_backend.py
tensorly/backend/numpy_backend.py
tensorly/backend/pytorch_backend.py
tensorly/backend/tensorflow_backend.py
tensorly/contrib/__init__.py
tensorly/contrib/decomposition/__init__.py
tensorly/contrib/decomposition/_tt_cross.py
tensorly/contrib/decomposition/tt_TTOI.py
tensorly/contrib/decomposition/tests/__init__.py
tensorly/contrib/decomposition/tests/test_mps_decomposition_cross.py
tensorly/contrib/decomposition/tests/test_tt_TTOI.py
tensorly/contrib/sparse/__init__.py
tensorly/contrib/sparse/core.py
tensorly/contrib/sparse/cp_tensor.py
tensorly/contrib/sparse/decomposition.py
tensorly/contrib/sparse/tenalg.py
tensorly/contrib/sparse/backend/__init__.py
tensorly/contrib/sparse/backend/numpy_backend.py
tensorly/contrib/sparse/tests/__init__.py
tensorly/contrib/sparse/tests/test_decomposition.py
tensorly/contrib/sparse/tests/test_tenalg.py
tensorly/datasets/__init__.py
tensorly/datasets/data_imports.py
tensorly/datasets/synthetic.py
tensorly/datasets/tests/__init__.py
tensorly/datasets/tests/test_imports.py
tensorly/datasets/tests/test_synthetic.py
tensorly/decomposition/__init__.py
tensorly/decomposition/_base_decomposition.py
tensorly/decomposition/_cmtf_als.py
tensorly/decomposition/_constrained_cp.py
tensorly/decomposition/_cp.py
tensorly/decomposition/_cp_power.py
tensorly/decomposition/_nn_cp.py
tensorly/decomposition/_parafac2.py
tensorly/decomposition/_symmetric_cp.py
tensorly/decomposition/_tr.py
tensorly/decomposition/_tt.py
tensorly/decomposition/_tucker.py
tensorly/decomposition/robust_decomposition.py
tensorly/decomposition/tests/__init__.py
tensorly-0.8.1.dist-info/AUTHORS.rst
tensorly-0.8.1.dist-info/LICENSE.txt
tensorly-0.8.1.dist-info/METADATA
tensorly-0.8.1.dist-info/WHEEL
tensorly-0.8.1.dist-info/top_level.txt
tensorly-0.8.1.dist-info/RECORD
