Metadata-Version: 2.1
Name: tensorly
Version: 0.8.1
Summary: Tensor learning in Python.
Home-page: https://github.com/tensorly/tensorly
Author: Jean Kossaifi
Author-email: jean.kossaifi@gmail.com
License: Modified BSD
Download-URL: https://github.com/tensorly/tensorly/tarball/0.8.1
Platform: UNKNOWN
Classifier: Topic :: Scientific/Engineering
Classifier: License :: OSI Approved :: BSD License
Classifier: Programming Language :: Python :: 3
License-File: LICENSE.txt
License-File: AUTHORS.rst
